python_utils/__init__.py
python_utils/_settings.py
python_utils/decorators.py
python_utils/types.py
utility_pi-0.1.0.dist-info/METADATA
utility_pi-0.1.0.dist-info/WHEEL
utility_pi-0.1.0.dist-info/top_level.txt
utility_pi-0.1.0.dist-info/RECORD
