Metadata-Version: 2.4
Name: utility-pi
Version: 0.1.0
Summary: Add your description here
Requires-Python: >=3.11
Requires-Dist: pyyaml>=6.0.3
